Metadata-Version: 2.4
Name: blender-mcp-MB
Version: 1.1.1
Summary: Blender integration through the Model Context Protocol
Author-email: Your Name <your.email@example.com>
License: MIT
Project-URL: Homepage, https://github.com/yourusername/blender-mcp
Project-URL: Bug Tracker, https://github.com/yourusername/blender-mcp/issues
Classifier: Programming Language :: Python :: 3
Classifier: License :: OSI Approved :: MIT License
Classifier: Operating System :: OS Independent
Requires-Python: >=3.10
License-File: LICENSE
Requires-Dist: mcp[cli]>=1.3.0
Dynamic: license-file
